fhaws/.DS_Store
fhaws/__init__.py
fhaws/aws_cost_usage.py
fhaws/ce.py
fhaws/cost-reporter.py
fhaws/cw.py
fhaws/ec2.py
fhaws/iam.py
fhaws/mfa_compliance_report.py
fhaws/org.py
fhaws/prom-aws-accounts-cost.py
fhaws/prom-aws-services-cost.py
fhaws/prom-aws-services-cost.py.old
fhaws/role_chain.py
fhaws/s3.py
fhaws/sts.py
fhaws/support.py
fhaws-0.3.4.dist-info/LICENSE
fhaws-0.3.4.dist-info/WHEEL
fhaws-0.3.4.dist-info/METADATA
fhaws-0.3.4.dist-info/RECORD
