Metadata-Version: 2.1
Name: fhaws
Version: 0.3.4
Summary: A module containing helper functions to make working with Boto3 and Amazon AWS easier with Python
Home-page: https://github.com/robert-mcdermott/fhaws
License: MIT
Keywords: AWS,Boto3
Author: Robert McDermott
Requires-Python: >=3.7,<4.0
Classifier: License :: OSI Approved :: MIT License
Classifier: Programming Language :: Python :: 3
Classifier: Programming Language :: Python :: 3.10
Classifier: Programming Language :: Python :: 3.7
Classifier: Programming Language :: Python :: 3.8
Classifier: Programming Language :: Python :: 3.9
Requires-Dist: boto3 (>=1.24.37,<2.0.0)
Project-URL: Repository, https://github.com/robert-mcdermott/fhaws
